{
  "experiment_name": "lotka_volterra",
  "benchmark": {
    "name": "lotka_volterra",
    "observed_data_seed": 42,
    "T_max": 30.0,
    "x0": 50,
    "y0": 100,
    "true_theta1": 0.5,
    "true_theta2": 0.025,
    "true_theta3": 0.025,
    "true_theta4": 0.5
  },
  "methods": ["async_propulate_abc", "pyabc_smc"],
  "inference": {
    "max_simulations": 50000,
    "n_workers": 48,
    "k": 100,
    "tol_init": 500000.0,
    "scheduler_type": "acceptance_rate",
    "perturbation_scale": 0.8
  },
  "execution": {
    "n_replicates": 10,
    "base_seed": 0
  },
  "plots": {
    "posterior": true,
    "archive_evolution": true
  }
}
